Workbook

Sheet Base
A1: CPF | B1: cliente | C1: Campanha | D1: estabelecimento | E1: Data_Contrato | F1: Status | G1: Usuário | H1: Telefone | I1: Celular | J1: Situação correta | K1: Considerar | L1: AnoMes
A2: 876.631.980-34 | B2: REJANE CECILIA DA SILVA | C2: Receptiva SAN | D2: 2.13 CREDIAGORA SANTO ANGELO | E2: 46296.372 | F2: Cliente em negociaÃ§Ã£o | G2: lucimara.stiler | H2: (51)991419285 | I2: (51)994119285 | J2: =IFERROR(INDEX(validador!$B$2:$B$13,MATCH(F2,validador!$A$2:$A$13,0)),"") -> Cliente em negociação | K2: =IFERROR(INDEX(validador!$C$2:$C$13,MATCH(J2,validador!$B$2:$B$13,0)),"") -> Ligação | L2: =IF(E2="","",YEAR(E2)&""&RIGHT("0"&MONTH(E2),2)) -> 202610
A3: 592.933.570-20 | B3: SIRLEI CAMARGO KRAEMER | C3: CRUZ ALTA INSS 50 A 200 | D3: 3.03 CREDIAGORA CRUZ ALTA | E3: 46296.374 | F3: Telefone invÃ¡lido | G3: gabriele.sg | H3: (55)99615113500false | I3: (55)996151135 | J3: =IFERROR(INDEX(validador!$B$2:$B$13,MATCH(F3,validador!$A$2:$A$13,0)),"") -> Telefone inválido | K3: =IFERROR(INDEX(validador!$C$2:$C$13,MATCH(J3,validador!$B$2:$B$13,0)),"") -> Telefone inválido | L3: =IF(E3="","",YEAR(E3)&""&RIGHT("0"&MONTH(E3),2)) -> 202610
A4: 310.346.320-00 | B4: JOSE ERICO STEFFENS | C4: RECEPTIVA LOJA DIGITAL | D4: 3.04 LOJA DIGITAL | E4: 46296.375 | F4: ProspecÃ§Ã£o | G4: FERNANDA.B | H4: (55)33333365 | I4: (55)997206025 | J4: =IFERROR(INDEX(validador!$B$2:$B$13,MATCH(F4,validador!$A$2:$A$13,0)),"") -> Prospecção | K4: =IFERROR(INDEX(validador!$C$2:$C$13,MATCH(J4,validador!$B$2:$B$13,0)),"") -> Prospecção | L4: =IF(E4="","",YEAR(E4)&""&RIGHT("0"&MONTH(E4),2)) -> 202610
A5: 001.041.250-63 | B5: MARIA INEIS DE LIMA ROSA | C5: Credito Pessoal SLG | D5: 2.04 CREDIAGORA SAO LUIZ GONZAGA | E5: 46296.376 | F5: Cliente sem interesse | G5: CHAIANE.T | H5: (55)98426094300false | I5: (55)984260943 | J5: =IFERROR(INDEX(validador!$B$2:$B$13,MATCH(F5,validador!$A$2:$A$13,0)),"") -> Cliente sem interesse | K5: =IFERROR(INDEX(validador!$C$2:$C$13,MATCH(J5,validador!$B$2:$B$13,0)),"") -> Ligação | L5: =IF(E5="","",YEAR(E5)&""&RIGHT("0"&MONTH(E5),2)) -> 202610
A6: 038.715.630-56 | B6: VANESSA DA SILVA SOARES ZOTT | C6: Receptivo TMA | D6: 2.07 CREDIAGORA TRES DE MAIO | E6: 46296.376 | F6: ProspecÃ§Ã£o | G6: eduardadahlen | H6: (55)997132131 | I6: (55)997132131 | J6: =IFERROR(INDEX(validador!$B$2:$B$13,MATCH(F6,validador!$A$2:$A$13,0)),"") -> Prospecção | K6: =IFERROR(INDEX(validador!$C$2:$C$13,MATCH(J6,validador!$B$2:$B$13,0)),"") -> Prospecção | L6: =IF(E6="","",YEAR(E6)&""&RIGHT("0"&MONTH(E6),2)) -> 202610
A7: 006.227.380-97 | B7: CLARICE LESSE RODRIGUES | C7: Receptivo TMA | D7: 2.07 CREDIAGORA TRES DE MAIO | E7: 46296.378 | F7: ProspecÃ§Ã£o | G7: eduardadahlen | H7: (55)999682727 | I7: (55)999682727 | J7: =IFERROR(INDEX(validador!$B$2:$B$13,MATCH(F7,validador!$A$2:$A$13,0)),"") -> Prospecção | K7: =IFERROR(INDEX(validador!$C$2:$C$13,MATCH(J7,validador!$B$2:$B$13,0)),"") -> Prospecção | L7: =IF(E7="","",YEAR(E7)&""&RIGHT("0"&MONTH(E7),2)) -> 202610
A8: 004.349.850-74 | B8: NARA LIDIANE BRUM | C8: Receptiva SRO | D8: 2.01 CREDIAGORA SANTA ROSA | E8: 46296.379 | F8: Cliente sem margem_INSS | G8: camila.b | H8: (55)981447411 | I8: (55)981447411 | J8: =IFERROR(INDEX(validador!$B$2:$B$13,MATCH(F8,validador!$A$2:$A$13,0)),"") -> Cliente sem margem INSS | K8: =IFERROR(INDEX(validador!$C$2:$C$13,MATCH(J8,validador!$B$2:$B$13,0)),"") -> Cliente sem margem INSS | L8: =IF(E8="","",YEAR(E8)&""&RIGHT("0"&MONTH(E8),2)) -> 202610
A9: 279.690.020-72 | B9: CARLOS ADAIL SCHERER | C9: SAN INSS MARG 30 A 300 | D9: 2.13 CREDIAGORA SANTO ANGELO | E9: 46296.38 | F9: envio de whatsapp | G9: nicoli.gb | H9: (55)3313576800false | I9: (55)999029339 | J9: =IFERROR(INDEX(validador!$B$2:$B$13,MATCH(F9,validador!$A$2:$A$13,0)),"") -> Envio de Whatsapp | K9: =IFERROR(INDEX(validador!$C$2:$C$13,MATCH(J9,validador!$B$2:$B$13,0)),"") -> Envio de Whatsapp | L9: =IF(E9="","",YEAR(E9)&""&RIGHT("0"&MONTH(E9),2)) -> 202610
A10: 415.025.310-20 | B10: EMILIA DE FATIMA LEMOS PAVAO DA SILVA | C10: SAN INSS 30+ | D10: 2.13 CREDIAGORA SANTO ANGELO | E10: 46296.381 | F10: ProspecÃ§Ã£o | G10: lucimara.stiler | H10: (55)3314125300false | I10: (55)991973504 | J10: =IFERROR(INDEX(validador!$B$2:$B$13,MATCH(F10,validador!$A$2:$A$13,0)),"") -> Prospecção | K10: =IFERROR(INDEX(validador!$C$2:$C$13,MATCH(J10,validador!$B$2:$B$13,0)),"") -> Prospecção | L10: =IF(E10="","",YEAR(E10)&""&RIGHT("0"&MONTH(E10),2)) -> 202610
A11: 533.146.110-72 | B11: EVA JUSSARA NOGUEIRA | C11: Receptiva SAN | D11: 2.13 CREDIAGORA SANTO ANGELO | E11: 46296.382 | F11: ProspecÃ§Ã£o | G11: karine.reis | H11: (47)99666987500false | I11: (47)996669875 | J11: =IFERROR(INDEX(validador!$B$2:$B$13,MATCH(F11,validador!$A$2:$A$13,0)),"") -> Prospecção | K11: =IFERROR(INDEX(validador!$C$2:$C$13,MATCH(J11,validador!$B$2:$B$13,0)),"") -> Prospecção | L11: =IF(E11="","",YEAR(E11)&""&RIGHT("0"&MONTH(E11),2)) -> 202610
A12: 354.990.870-91 | B12: ADEMAR VILSON HOLZLE | C12: RECEPTIVA LOJA DIGITAL | D12: 3.04 LOJA DIGITAL | E12: 46296.382 | F12: Cliente sem interesse | G12: FERNANDA.B | H12: (55)996804677 | I12: (55)996804677 | J12: =IFERROR(INDEX(validador!$B$2:$B$13,MATCH(F12,validador!$A$2:$A$13,0)),"") -> Cliente sem interesse | K12: =IFERROR(INDEX(validador!$C$2:$C$13,MATCH(J12,validador!$B$2:$B$13,0)),"") -> Ligação | L12: =IF(E12="","",YEAR(E12)&""&RIGHT("0"&MONTH(E12),2)) -> 202610
A13: 005.671.270-79 | B13: LEONI MULLICH | C13: SAN INSS 30+ | D13: 2.13 CREDIAGORA SANTO ANGELO | E13: 46296.382 | F13: Cliente sem interesse | G13: lucimara.stiler | I13: (55)996626612 | J13: =IFERROR(INDEX(validador!$B$2:$B$13,MATCH(F13,validador!$A$2:$A$13,0)),"") -> Cliente sem interesse | K13: =IFERROR(INDEX(validador!$C$2:$C$13,MATCH(J13,validador!$B$2:$B$13,0)),"") -> Ligação | L13: =IF(E13="","",YEAR(E13)&""&RIGHT("0"&MONTH(E13),2)) -> 202610
A14: 006.227.380-97 | B14: CLARICE LESSE RODRIGUES | C14: Receptivo TMA | D14: 2.07 CREDIAGORA TRES DE MAIO | E14: 46296.382 | F14: ProspecÃ§Ã£o | G14: eduardadahlen | H14: (55)999682727 | I14: (55)999682727 | J14: =IFERROR(INDEX(validador!$B$2:$B$13,MATCH(F14,validador!$A$2:$A$13,0)),"") -> Prospecção | K14: =IFERROR(INDEX(validador!$C$2:$C$13,MATCH(J14,validador!$B$2:$B$13,0)),"") -> Prospecção | L14: =IF(E14="","",YEAR(E14)&""&RIGHT("0"&MONTH(E14),2)) -> 202610
A15: 214.127.400-10 | B15: UGO MACHADO | C15: Receptivo SCR | D15: 2.05 CREDIAGORA SANTO CRISTO | E15: 46296.384 | F15: ProspecÃ§Ã£o | G15: patricia.eu | H15: (55)999466340 | I15: (55)999466340 | J15: =IFERROR(INDEX(validador!$B$2:$B$13,MATCH(F15,validador!$A$2:$A$13,0)),"") -> Prospecção | K15: =IFERROR(INDEX(validador!$C$2:$C$13,MATCH(J15,validador!$B$2:$B$13,0)),"") -> Prospecção | L15: =IF(E15="","",YEAR(E15)&""&RIGHT("0"&MONTH(E15),2)) -> 202610
A16: 360.872.030-87 | B16: JANDIRA OLIVEIRA BOTTEGA | C16: CRUZ ALTA INSS 50 A 200 | D16: 3.03 CREDIAGORA CRUZ ALTA | E16: 46296.384 | F16: envio de whatsapp | G16: gabriele.sg | H16: (55)99717395600false | I16: (55)997173956 | J16: =IFERROR(INDEX(validador!$B$2:$B$13,MATCH(F16,validador!$A$2:$A$13,0)),"") -> Envio de Whatsapp | K16: =IFERROR(INDEX(validador!$C$2:$C$13,MATCH(J16,validador!$B$2:$B$13,0)),"") -> Envio de Whatsapp | L16: =IF(E16="","",YEAR(E16)&""&RIGHT("0"&MONTH(E16),2)) -> 202610
A17: 607.257.700-82 | B17: NILDA MARIA DA SILVA ADOLPHO | C17: Receptiva TPO | D17: 2.14 CREDIAGORA TENENTE PORTELA | E17: 46296.384 | F17: Cliente sem margem_INSS | G17: mirian.silveira | H17: (51)982624349 | J17: =IFERROR(INDEX(validador!$B$2:$B$13,MATCH(F17,validador!$A$2:$A$13,0)),"") -> Cliente sem margem INSS | K17: =IFERROR(INDEX(validador!$C$2:$C$13,MATCH(J17,validador!$B$2:$B$13,0)),"") -> Cliente sem margem INSS | L17: =IF(E17="","",YEAR(E17)&""&RIGHT("0"&MONTH(E17),2)) -> 202610
A18: 008.086.970-05 | B18: JULIA EMILIO | C18: TPO INSS 50,00 A 150,00 | D18: 2.14 CREDIAGORA TENENTE PORTELA | E18: 46296.386 | F18: Cliente com restriÃ§Ã£o | G18: kelen.tnp | H18: (55)99973116600false | I18: (55)997337605 | J18: =IFERROR(INDEX(validador!$B$2:$B$13,MATCH(F18,validador!$A$2:$A$13,0)),"") -> Cliente com restrição | K18: =IFERROR(INDEX(validador!$C$2:$C$13,MATCH(J18,validador!$B$2:$B$13,0)),"") -> Cliente com restrição | L18: =IF(E18="","",YEAR(E18)&""&RIGHT("0"&MONTH(E18),2)) -> 202610
A19: 346.835.180-15 | B19: SENAIDE SCHROER | C19: CRUZ ALTA INSS 50 A 200 | D19: 3.03 CREDIAGORA CRUZ ALTA | E19: 46296.387 | F19: Cliente sem interesse | G19: gabriele.sg | H19: (55)991541106020false | I19: (55)991541106 | J19: =IFERROR(INDEX(validador!$B$2:$B$13,MATCH(F19,validador!$A$2:$A$13,0)),"") -> Cliente sem interesse | K19: =IFERROR(INDEX(validador!$C$2:$C$13,MATCH(J19,validador!$B$2:$B$13,0)),"") -> Ligação | L19: =IF(E19="","",YEAR(E19)&""&RIGHT("0"&MONTH(E19),2)) -> 202610
A20: 022.118.170-92 | B20: MAURICIO RIBEIRO CAMARGO | C20: CLT IJUI | D20: 2.06 CREDIAGORA IJUI | E20: 46296.388 | F20: ProspecÃ§Ã£o | G20: camila.froes | H20: (0)0 | I20: (55)991799076 | J20: =IFERROR(INDEX(validador!$B$2:$B$13,MATCH(F20,validador!$A$2:$A$13,0)),"") -> Prospecção | K20: =IFERROR(INDEX(validador!$C$2:$C$13,MATCH(J20,validador!$B$2:$B$13,0)),"") -> Prospecção | L20: =IF(E20="","",YEAR(E20)&""&RIGHT("0"&MONTH(E20),2)) -> 202610
A21: 839.745.980-49 | B21: MARI MADALENA DO NASCIMENTO | C21: TPO INSS 50,00 A 150,00 | D21: 2.14 CREDIAGORA TENENTE PORTELA | E21: 46296.389 | F21: Cliente com restriÃ§Ã£o | G21: kelen.tnp | H21: (55)35222533 | I21: (55)997324105 | J21: =IFERROR(INDEX(validador!$B$2:$B$13,MATCH(F21,validador!$A$2:$A$13,0)),"") -> Cliente com restrição | K21: =IFERROR(INDEX(validador!$C$2:$C$13,MATCH(J21,validador!$B$2:$B$13,0)),"") -> Cliente com restrição | L21: =IF(E21="","",YEAR(E21)&""&RIGHT("0"&MONTH(E21),2)) -> 202610
A22: 384.772.380-49 | B22: JOAO ADELMO LISBOA | C22: Receptivo SCR | D22: 2.05 CREDIAGORA SANTO CRISTO | E22: 46296.389 | F22: Cliente em negociaÃ§Ã£o | G22: amanda.m | H22: (55)99081800 | I22: (55)996661932 | J22: =IFERROR(INDEX(validador!$B$2:$B$13,MATCH(F22,validador!$A$2:$A$13,0)),"") -> Cliente em negociação | K22: =IFERROR(INDEX(validador!$C$2:$C$13,MATCH(J22,validador!$B$2:$B$13,0)),"") -> Ligação | L22: =IF(E22="","",YEAR(E22)&""&RIGHT("0"&MONTH(E22),2)) -> 202610
A23: 375.332.400-06 | B23: ALGEU DAGORT | C23: RECEPTIVA LOJA DIGITAL | D23: 3.04 LOJA DIGITAL | E23: 46296.389 | F23: ProspecÃ§Ã£o | G23: FERNANDA.B | H23: (55)99961803700false | I23: (55)999618037 | J23: =IFERROR(INDEX(validador!$B$2:$B$13,MATCH(F23,validador!$A$2:$A$13,0)),"") -> Prospecção | K23: =IFERROR(INDEX(validador!$C$2:$C$13,MATCH(J23,validador!$B$2:$B$13,0)),"") -> Prospecção | L23: =IF(E23="","",YEAR(E23)&""&RIGHT("0"&MONTH(E23),2)) -> 202610
A24: 308.839.700-15 | B24: ARMINDO GORAL | C24: Receptiva SRO | D24: 2.01 CREDIAGORA SANTA ROSA | E24: 46296.39 | F24: ProspecÃ§Ã£o | G24: TALIAF | H24: (55)99963165270false | I24: (55)999631652 | J24: =IFERROR(INDEX(validador!$B$2:$B$13,MATCH(F24,validador!$A$2:$A$13,0)),"") -> Prospecção | K24: =IFERROR(INDEX(validador!$C$2:$C$13,MATCH(J24,validador!$B$2:$B$13,0)),"") -> Prospecção | L24: =IF(E24="","",YEAR(E24)&""&RIGHT("0"&MONTH(E24),2)) -> 202610
A25: 012.501.740-58 | B25: DALVA BEATRIZ FEIDEN KOLLING | C25: Receptiva SRO | D25: 2.01 CREDIAGORA SANTA ROSA | E25: 46296.391 | F25: Cliente sem interesse | G25: TALIAF | H25: (55)99685327 | I25: (55)996853273 | J25: =IFERROR(INDEX(validador!$B$2:$B$13,MATCH(F25,validador!$A$2:$A$13,0)),"") -> Cliente sem interesse | K25: =IFERROR(INDEX(validador!$C$2:$C$13,MATCH(J25,validador!$B$2:$B$13,0)),"") -> Ligação | L25: =IF(E25="","",YEAR(E25)&""&RIGHT("0"&MONTH(E25),2)) -> 202610
A26: 354.990.870-91 | B26: ADEMAR VILSON HOLZLE | C26: Receptivo IJUI | D26: 2.06 CREDIAGORA IJUI | E26: 46296.391 | F26: Cliente em negociaÃ§Ã£o | G26: neusa_credi | H26: (55)996804677 | I26: (55)996804677 | J26: =IFERROR(INDEX(validador!$B$2:$B$13,MATCH(F26,validador!$A$2:$A$13,0)),"") -> Cliente em negociação | K26: =IFERROR(INDEX(validador!$C$2:$C$13,MATCH(J26,validador!$B$2:$B$13,0)),"") -> Ligação | L26: =IF(E26="","",YEAR(E26)&""&RIGHT("0"&MONTH(E26),2)) -> 202610
A27: 686.065.830-49 | B27: SUSANA MARIA DE QUADROS OLIVEIRA | C27: Receptiva SRO | D27: 2.01 CREDIAGORA SANTA ROSA | E27: 46296.391 | F27: Cliente sem margem_INSS | G27: camila.b | H27: (51)980511946020false | I27: (51)980511946 | J27: =IFERROR(INDEX(validador!$B$2:$B$13,MATCH(F27,validador!$A$2:$A$13,0)),"") -> Cliente sem margem INSS | K27: =IFERROR(INDEX(validador!$C$2:$C$13,MATCH(J27,validador!$B$2:$B$13,0)),"") -> Cliente sem margem INSS | L27: =IF(E27="","",YEAR(E27)&""&RIGHT("0"&MONTH(E27),2)) -> 202610
A28: 021.599.410-85 | B28: CLAITON SOMAVILLA | C28: CLT IJUI | D28: 2.06 CREDIAGORA IJUI | E28: 46296.391 | F28: ProspecÃ§Ã£o | G28: camila.froes | H28: (55)996520957 | I28: (55)996520957 | J28: =IFERROR(INDEX(validador!$B$2:$B$13,MATCH(F28,validador!$A$2:$A$13,0)),"") -> Prospecção | K28: =IFERROR(INDEX(validador!$C$2:$C$13,MATCH(J28,validador!$B$2:$B$13,0)),"") -> Prospecção | L28: =IF(E28="","",YEAR(E28)&""&RIGHT("0"&MONTH(E28),2)) -> 202610
A29: 993.625.200-44 | B29: IVONE MARIA MAGERL | C29: Receptivo SCR | D29: 2.05 CREDIAGORA SANTO CRISTO | E29: 46296.392 | F29: ProspecÃ§Ã£o | G29: patricia.eu | H29: (55)35411260 | I29: (55)999464349 | J29: =IFERROR(INDEX(validador!$B$2:$B$13,MATCH(F29,validador!$A$2:$A$13,0)),"") -> Prospecção | K29: =IFERROR(INDEX(validador!$C$2:$C$13,MATCH(J29,validador!$B$2:$B$13,0)),"") -> Prospecção | L29: =IF(E29="","",YEAR(E29)&""&RIGHT("0"&MONTH(E29),2)) -> 202610
... A45: 670.939.300-34 | B45: VARONEZ WERNER | C45: TPO INSS 50,00 A 150,00 | D45: 2.14 CREDIAGORA TENENTE PORTELA | E45: 46296.401 | F45: Cliente em negociaÃ§Ã£o | G45: kelen.tnp | H45: (55)99605884800false | I45: (55)997010269 | J45: =IFERROR(INDEX(validador!$B$2:$B$13,MATCH(F45,validador!$A$2:$A$13,0)),"") -> Cliente em negociação | K45: =IFERROR(INDEX(validador!$C$2:$C$13,MATCH(J45,validador!$B$2:$B$13,0)),"") -> Ligação | L45: =IF(E45="","",YEAR(E45)&""&RIGHT("0"&MONTH(E45),2)) -> 202610
A46: 193.114.270-04 | B46: ODETE PACHECO BONORINO | C46: Receptiva SRO | D46: 2.01 CREDIAGORA SANTA ROSA | E46: 46296.401 | F46: Cliente sem margem_INSS | G46: camila.b | H46: (51)3680423200false | J46: =IFERROR(INDEX(validador!$B$2:$B$13,MATCH(F46,validador!$A$2:$A$13,0)),"") -> Cliente sem margem INSS | K46: =IFERROR(INDEX(validador!$C$2:$C$13,MATCH(J46,validador!$B$2:$B$13,0)),"") -> Cliente sem margem INSS | L46: =IF(E46="","",YEAR(E46)&""&RIGHT("0"&MONTH(E46),2)) -> 202610
A47: 244.873.090-34 | B47: ADEMAR PINTO MOREIRA | C47: CRUZ ALTA INSS 50 A 200 | D47: 3.03 CREDIAGORA CRUZ ALTA | E47: 46296.401 | F47: envio de whatsapp | G47: gabriele.sg | H47: (55)98169861100false | I47: (55)981301726 | J47: =IFERROR(INDEX(validador!$B$2:$B$13,MATCH(F47,validador!$A$2:$A$13,0)),"") -> Envio de Whatsapp | K47: =IFERROR(INDEX(validador!$C$2:$C$13,MATCH(J47,validador!$B$2:$B$13,0)),"") -> Envio de Whatsapp | L47: =IF(E47="","",YEAR(E47)&""&RIGHT("0"&MONTH(E47),2)) -> 202610
A48: 997.056.300-97 | B48: NELSI PREUSS DORNELLES | C48: Receptivo SCR | D48: 2.05 CREDIAGORA SANTO CRISTO | E48: 46296.401 | F48: ProspecÃ§Ã£o | G48: patricia.eu | H48: (55)984085014 | I48: (55)984085014 | J48: =IFERROR(INDEX(validador!$B$2:$B$13,MATCH(F48,validador!$A$2:$A$13,0)),"") -> Prospecção | K48: =IFERROR(INDEX(validador!$C$2:$C$13,MATCH(J48,validador!$B$2:$B$13,0)),"") -> Prospecção | L48: =IF(E48="","",YEAR(E48)&""&RIGHT("0"&MONTH(E48),2)) -> 202610
A49: 006.991.910-09 | B49: MARCOS RODRIGO CORREA | C49: Receptiva SAN | D49: 2.13 CREDIAGORA SANTO ANGELO | E49: 46296.401 | F49: Cliente com restriÃ§Ã£o | G49: karine.reis | H49: (51)995036565 | I49: (51)995036565 | J49: =IFERROR(INDEX(validador!$B$2:$B$13,MATCH(F49,validador!$A$2:$A$13,0)),"") -> Cliente com restrição | K49: =IFERROR(INDEX(validador!$C$2:$C$13,MATCH(J49,validador!$B$2:$B$13,0)),"") -> Cliente com restrição | L49: =IF(E49="","",YEAR(E49)&""&RIGHT("0"&MONTH(E49),2)) -> 202610
A50: 678.484.860-87 | B50: FILOMENA ROESCH | C50: TPO INSS 50,00 A 150,00 | D50: 2.14 CREDIAGORA TENENTE PORTELA | E50: 46296.401 | F50: Agendado atendimento em loja | G50: mirian.silveira | H50: (55)93616306 | I50: (51)995005798 | J50: =IFERROR(INDEX(validador!$B$2:$B$13,MATCH(F50,validador!$A$2:$A$13,0)),"") -> Agendado atendimento em loja | K50: =IFERROR(INDEX(validador!$C$2:$C$13,MATCH(J50,validador!$B$2:$B$13,0)),"") -> Ligação | L50: =IF(E50="","",YEAR(E50)&""&RIGHT("0"&MONTH(E50),2)) -> 202610
A51: 603.536.000-91 | B51: ELISANGELA FRANCO SILVEIRA | C51: CLT IJUI | D51: 2.06 CREDIAGORA IJUI | E51: 46296.401 | F51: ProspecÃ§Ã£o | G51: camila.froes | H51: (0)0 | I51: (55)992096667 | J51: =IFERROR(INDEX(validador!$B$2:$B$13,MATCH(F51,validador!$A$2:$A$13,0)),"") -> Prospecção | K51: =IFERROR(INDEX(validador!$C$2:$C$13,MATCH(J51,validador!$B$2:$B$13,0)),"") -> Prospecção | L51: =IF(E51="","",YEAR(E51)&""&RIGHT("0"&MONTH(E51),2)) -> 202610
A52: 346.835.180-15 | B52: SENAIDE SCHROER | C52: RECEPTIVA LOJA DIGITAL | D52: 3.04 LOJA DIGITAL | E52: 46296.402 | F52: Cliente sem interesse | G52: FERNANDA.B | H52: (55)991541106020false | I52: (55)991541106 | J52: =IFERROR(INDEX(validador!$B$2:$B$13,MATCH(F52,validador!$A$2:$A$13,0)),"") -> Cliente sem interesse | K52: =IFERROR(INDEX(validador!$C$2:$C$13,MATCH(J52,validador!$B$2:$B$13,0)),"") -> Ligação | L52: =IF(E52="","",YEAR(E52)&""&RIGHT("0"&MONTH(E52),2)) -> 202610
A53: 968.621.300-72 | B53: IVETE RODRIGUES CAVALLARI | C53: TPO INSS 50,00 A 150,00 | D53: 2.14 CREDIAGORA TENENTE PORTELA | E53: 46296.402 | F53: Telefone invÃ¡lido | G53: mirian.silveira | H53: (55)996047592 | I53: (55)997083947 | J53: =IFERROR(INDEX(validador!$B$2:$B$13,MATCH(F53,validador!$A$2:$A$13,0)),"") -> Telefone inválido | K53: =IFERROR(INDEX(validador!$C$2:$C$13,MATCH(J53,validador!$B$2:$B$13,0)),"") -> Telefone inválido | L53: =IF(E53="","",YEAR(E53)&""&RIGHT("0"&MONTH(E53),2)) -> 202610
A54: 011.642.730-27 | B54: CLEITON TIAGO ORTH | C54: Receptivo SCR | D54: 2.05 CREDIAGORA SANTO CRISTO | E54: 46296.403 | F54: ProspecÃ§Ã£o | G54: amanda.m | H54: (55)999674448 | I54: (55)999674448 | J54: =IFERROR(INDEX(validador!$B$2:$B$13,MATCH(F54,validador!$A$2:$A$13,0)),"") -> Prospecção | K54: =IFERROR(INDEX(validador!$C$2:$C$13,MATCH(J54,validador!$B$2:$B$13,0)),"") -> Prospecção | L54: =IF(E54="","",YEAR(E54)&""&RIGHT("0"&MONTH(E54),2)) -> 202610
A55: 382.645.440-53 | B55: GILMAR VENDRUSCOLLO | C55: TPO INSS 50,00 A 150,00 | D55: 2.14 CREDIAGORA TENENTE PORTELA | E55: 46296.403 | F55: envio de whatsapp | G55: mirian.silveira | H55: (55)996523832 | I55: (55)996523832 | J55: =IFERROR(INDEX(validador!$B$2:$B$13,MATCH(F55,validador!$A$2:$A$13,0)),"") -> Envio de Whatsapp | K55: =IFERROR(INDEX(validador!$C$2:$C$13,MATCH(J55,validador!$B$2:$B$13,0)),"") -> Envio de Whatsapp | L55: =IF(E55="","",YEAR(E55)&""&RIGHT("0"&MONTH(E55),2)) -> 202610
A56: 975.057.900-30 | B56: ADEMIR FAGUNDES DE OLIVEIRA | C56: TPO INSS 50,00 A 150,00 | D56: 2.14 CREDIAGORA TENENTE PORTELA | E56: 46296.403 | F56: ProspecÃ§Ã£o | G56: mirian.silveira | H56: (55)99661636800false | I56: (55)996616368 | J56: =IFERROR(INDEX(validador!$B$2:$B$13,MATCH(F56,validador!$A$2:$A$13,0)),"") -> Prospecção | K56: =IFERROR(INDEX(validador!$C$2:$C$13,MATCH(J56,validador!$B$2:$B$13,0)),"") -> Prospecção | L56: =IF(E56="","",YEAR(E56)&""&RIGHT("0"&MONTH(E56),2)) -> 202610
A57: 727.010.800-53 | B57: PAULO DE ANDRADE | C57: Receptivo SCR | D57: 2.05 CREDIAGORA SANTO CRISTO | E57: 46296.403 | F57: ProspecÃ§Ã£o | G57: patricia.eu | H57: (55)999971480 | I57: (55)999971480 | J57: =IFERROR(INDEX(validador!$B$2:$B$13,MATCH(F57,validador!$A$2:$A$13,0)),"") -> Prospecção | K57: =IFERROR(INDEX(validador!$C$2:$C$13,MATCH(J57,validador!$B$2:$B$13,0)),"") -> Prospecção | L57: =IF(E57="","",YEAR(E57)&""&RIGHT("0"&MONTH(E57),2)) -> 202610
A58: 015.646.290-74 | B58: ALEXANDRE DOS SANTOS GARCIA | C58: Credito Pessoal SLG | D58: 2.04 CREDIAGORA SAO LUIZ GONZAGA | E58: 46296.403 | F58: Cliente sem interesse | G58: CHAIANE.T | H58: (55)999348023 | I58: (55)999348023 | J58: =IFERROR(INDEX(validador!$B$2:$B$13,MATCH(F58,validador!$A$2:$A$13,0)),"") -> Cliente sem interesse | K58: =IFERROR(INDEX(validador!$C$2:$C$13,MATCH(J58,validador!$B$2:$B$13,0)),"") -> Ligação | L58: =IF(E58="","",YEAR(E58)&""&RIGHT("0"&MONTH(E58),2)) -> 202610
... A61: 406.665.300-68 | B61: MARISTELA DIAS NUNES | C61: CRUZ ALTA INSS 50 A 200 | D61: 3.03 CREDIAGORA CRUZ ALTA | E61: 46296.405 | F61: envio de whatsapp | G61: gabriele.sg | H61: (55)98409979670false | I61: (55)992211807 | J61: =IFERROR(INDEX(validador!$B$2:$B$13,MATCH(F61,validador!$A$2:$A$13,0)),"") -> Envio de Whatsapp | K61: =IFERROR(INDEX(validador!$C$2:$C$13,MATCH(J61,validador!$B$2:$B$13,0)),"") -> Envio de Whatsapp | L61: =IF(E61="","",YEAR(E61)&""&RIGHT("0"&MONTH(E61),2)) -> 202610
A62: 854.435.570-68 | B62: PRISCILA PIRES MARÇAL | C62: Receptiva SAN | D62: 2.13 CREDIAGORA SANTO ANGELO | E62: 46296.405 | F62: Cliente em negociaÃ§Ã£o | G62: karine.reis | J62: =IFERROR(INDEX(validador!$B$2:$B$13,MATCH(F62,validador!$A$2:$A$13,0)),"") -> Cliente em negociação | K62: =IFERROR(INDEX(validador!$C$2:$C$13,MATCH(J62,validador!$B$2:$B$13,0)),"") -> Ligação | L62: =IF(E62="","",YEAR(E62)&""&RIGHT("0"&MONTH(E62),2)) -> 202610
A63: 039.480.310-88 | B63: ALINE LURDES DOS SANTOS | C63: Receptivo SCR | D63: 2.05 CREDIAGORA SANTO CRISTO | E63: 46296.405 | F63: ProspecÃ§Ã£o | G63: amanda.m | H63: (55)996503188 | I63: (55)996503188 | J63: =IFERROR(INDEX(validador!$B$2:$B$13,MATCH(F63,validador!$A$2:$A$13,0)),"") -> Prospecção | K63: =IFERROR(INDEX(validador!$C$2:$C$13,MATCH(J63,validador!$B$2:$B$13,0)),"") -> Prospecção | L63: =IF(E63="","",YEAR(E63)&""&RIGHT("0"&MONTH(E63),2)) -> 202610
A64: 767.016.380-15 | B64: VALDENIR TRIVIZIOL PINHEIRO | C64: RECEPTIVA LOJA DIGITAL | D64: 3.04 LOJA DIGITAL | E64: 46296.406 | F64: Agendado atendimento em loja | G64: FERNANDA.B | H64: (55)999570264 | I64: (55)999570264 | J64: =IFERROR(INDEX(validador!$B$2:$B$13,MATCH(F64,validador!$A$2:$A$13,0)),"") -> Agendado atendimento em loja | K64: =IFERROR(INDEX(validador!$C$2:$C$13,MATCH(J64,validador!$B$2:$B$13,0)),"") -> Ligação | L64: =IF(E64="","",YEAR(E64)&""&RIGHT("0"&MONTH(E64),2)) -> 202610
A65: 003.080.550-39 | B65: JOCEMARA PLACIDO NUNES | C65: CLT IJUI | D65: 2.06 CREDIAGORA IJUI | E65: 46296.407 | F65: ProspecÃ§Ã£o | G65: camila.froes | H65: (0)0 | I65: (55)999540207 | J65: =IFERROR(INDEX(validador!$B$2:$B$13,MATCH(F65,validador!$A$2:$A$13,0)),"") -> Prospecção | K65: =IFERROR(INDEX(validador!$C$2:$C$13,MATCH(J65,validador!$B$2:$B$13,0)),"") -> Prospecção | L65: =IF(E65="","",YEAR(E65)&""&RIGHT("0"&MONTH(E65),2)) -> 202610
A66: 044.785.890-46 | B66: MINEIA VANESSA ROBE | C66: Receptivo SCR | D66: 2.05 CREDIAGORA SANTO CRISTO | E66: 46296.407 | F66: Agendado atendimento em loja | G66: patricia.eu | H66: (55)997037176 | I66: (55)997037176 | J66: =IFERROR(INDEX(validador!$B$2:$B$13,MATCH(F66,validador!$A$2:$A$13,0)),"") -> Agendado atendimento em loja | K66: =IFERROR(INDEX(validador!$C$2:$C$13,MATCH(J66,validador!$B$2:$B$13,0)),"") -> Ligação | L66: =IF(E66="","",YEAR(E66)&""&RIGHT("0"&MONTH(E66),2)) -> 202610
A67: 008.729.660-89 | B67: CLAIR TERESINHA WASMUTH | C67: TPO INSS 50,00 A 150,00 | D67: 2.14 CREDIAGORA TENENTE PORTELA | E67: 46296.407 | F67: Cliente com restriÃ§Ã£o | G67: anapaula | H67: (55)999121211 | I67: (55)999121211 | J67: =IFERROR(INDEX(validador!$B$2:$B$13,MATCH(F67,validador!$A$2:$A$13,0)),"") -> Cliente com restrição | K67: =IFERROR(INDEX(validador!$C$2:$C$13,MATCH(J67,validador!$B$2:$B$13,0)),"") -> Cliente com restrição | L67: =IF(E67="","",YEAR(E67)&""&RIGHT("0"&MONTH(E67),2)) -> 202610
A68: 351.030.860-34 | B68: NILTON RIOS PILAR | C68: Receptivo ALEG | D68: 2.10 CREDIAGORA ALEGRETE | E68: 46296.407 | F68: Cliente com restriÃ§Ã£o | G68: queilla.r | H68: (55)997068925 | I68: (55)997068925 | J68: =IFERROR(INDEX(validador!$B$2:$B$13,MATCH(F68,validador!$A$2:$A$13,0)),"") -> Cliente com restrição | K68: =IFERROR(INDEX(validador!$C$2:$C$13,MATCH(J68,validador!$B$2:$B$13,0)),"") -> Cliente com restrição | L68: =IF(E68="","",YEAR(E68)&""&RIGHT("0"&MONTH(E68),2)) -> 202610
A69: 802.807.810-91 | B69: DEFFERSON LUIS MENEZES DOS REIS | C69: Receptiva URU | D69: 3.02 CREDIAGORA URUGUAIANA | E69: 46296.409 | F69: ProspecÃ§Ã£o | G69: andreia.rospa | H69: (55)98453668000false | I69: (55)984536680 | J69: =IFERROR(INDEX(validador!$B$2:$B$13,MATCH(F69,validador!$A$2:$A$13,0)),"") -> Prospecção | K69: =IFERROR(INDEX(validador!$C$2:$C$13,MATCH(J69,validador!$B$2:$B$13,0)),"") -> Prospecção | L69: =IF(E69="","",YEAR(E69)&""&RIGHT("0"&MONTH(E69),2)) -> 202610
A70: 010.983.360-03 | B70: MARILEI INES WERLANG BACH | C70: Receptivo SCR | D70: 2.05 CREDIAGORA SANTO CRISTO | E70: 46296.409 | F70: ProspecÃ§Ã£o | G70: amanda.m | H70: (55)984341482 | I70: (55)984341482 | J70: =IFERROR(INDEX(validador!$B$2:$B$13,MATCH(F70,validador!$A$2:$A$13,0)),"") -> Prospecção | K70: =IFERROR(INDEX(validador!$C$2:$C$13,MATCH(J70,validador!$B$2:$B$13,0)),"") -> Prospecção | L70: =IF(E70="","",YEAR(E70)&""&RIGHT("0"&MONTH(E70),2)) -> 202610
A71: 990.598.940-49 | B71: ANA GRACIELA SCHAEFER | C71: Receptivo SCR | D71: 2.05 CREDIAGORA SANTO CRISTO | E71: 46296.409 | F71: ProspecÃ§Ã£o | G71: amanda.m | H71: (55)35411341 | I71: (55)984578724 | J71: =IFERROR(INDEX(validador!$B$2:$B$13,MATCH(F71,validador!$A$2:$A$13,0)),"") -> Prospecção | K71: =IFERROR(INDEX(validador!$C$2:$C$13,MATCH(J71,validador!$B$2:$B$13,0)),"") -> Prospecção | L71: =IF(E71="","",YEAR(E71)&""&RIGHT("0"&MONTH(E71),2)) -> 202610
A72: 024.188.310-51 | B72: CLECI DE FATIMA BILHALVA | C72: Receptivo SCR | D72: 2.05 CREDIAGORA SANTO CRISTO | E72: 46296.409 | F72: ProspecÃ§Ã£o | G72: amanda.m | H72: (55)984760135 | I72: (55)984760135 | J72: =IFERROR(INDEX(validador!$B$2:$B$13,MATCH(F72,validador!$A$2:$A$13,0)),"") -> Prospecção | K72: =IFERROR(INDEX(validador!$C$2:$C$13,MATCH(J72,validador!$B$2:$B$13,0)),"") -> Prospecção | L72: =IF(E72="","",YEAR(E72)&""&RIGHT("0"&MONTH(E72),2)) -> 202610
A73: 305.323.530-72 | B73: GILMAR ANTONIO MAFFI | C73: PARATY ENT JAN A JUNHO | D73: 3.01 PARATYCRED | E73: 46296.409 | F73: Aceitou NegociaÃ§Ã£o | G73: andre.prt | H73: (55)99138110800false | I73: (55)992088468 | J73: =IFERROR(INDEX(validador!$B$2:$B$13,MATCH(F73,validador!$A$2:$A$13,0)),"") -> Aceitou Negociação | K73: =IFERROR(INDEX(validador!$C$2:$C$13,MATCH(J73,validador!$B$2:$B$13,0)),"") -> Ligação | L73: =IF(E73="","",YEAR(E73)&""&RIGHT("0"&MONTH(E73),2)) -> 202610
A74: 759.166.900-10 | B74: LOURDES TERESINHA LEAL FABRIZIO | C74: SAN INSS 30+ | D74: 2.13 CREDIAGORA SANTO ANGELO | E74: 46296.41 | F74: ProspecÃ§Ã£o | G74: lucimara.stiler | H74: (55)99910795400false | I74: (55)999107954 | J74: =IFERROR(INDEX(validador!$B$2:$B$13,MATCH(F74,validador!$A$2:$A$13,0)),"") -> Prospecção | K74: =IFERROR(INDEX(validador!$C$2:$C$13,MATCH(J74,validador!$B$2:$B$13,0)),"") -> Prospecção | L74: =IF(E74="","",YEAR(E74)&""&RIGHT("0"&MONTH(E74),2)) -> 202610
... A92: 048.497.460-20 | B92: DYANA GABRIELI STAADTLOBER | C92: Receptivo SCR | D92: 2.05 CREDIAGORA SANTO CRISTO | E92: 46296.413 | F92: ProspecÃ§Ã£o | G92: amanda.m | H92: (55)997150577 | I92: (55)997150577 | J92: =IFERROR(INDEX(validador!$B$2:$B$13,MATCH(F92,validador!$A$2:$A$13,0)),"") -> Prospecção | K92: =IFERROR(INDEX(validador!$C$2:$C$13,MATCH(J92,validador!$B$2:$B$13,0)),"") -> Prospecção | L92: =IF(E92="","",YEAR(E92)&""&RIGHT("0"&MONTH(E92),2)) -> 202610
A93: 066.446.270-72 | B93: VIVIANA INES MARTIS | C93: Receptivo SCR | D93: 2.05 CREDIAGORA SANTO CRISTO | E93: 46296.413 | F93: ProspecÃ§Ã£o | G93: amanda.m | I93: (55)984480660 | J93: =IFERROR(INDEX(validador!$B$2:$B$13,MATCH(F93,validador!$A$2:$A$13,0)),"") -> Prospecção | K93: =IFERROR(INDEX(validador!$C$2:$C$13,MATCH(J93,validador!$B$2:$B$13,0)),"") -> Prospecção | L93: =IF(E93="","",YEAR(E93)&""&RIGHT("0"&MONTH(E93),2)) -> 202610
A94: 066.202.640-34 | B94: YESSICA FLORENCIA DE RAMOS | C94: Receptivo SCR | D94: 2.05 CREDIAGORA SANTO CRISTO | E94: 46296.414 | F94: ProspecÃ§Ã£o | G94: amanda.m | I94: (55)984480603 | J94: =IFERROR(INDEX(validador!$B$2:$B$13,MATCH(F94,validador!$A$2:$A$13,0)),"") -> Prospecção | K94: =IFERROR(INDEX(validador!$C$2:$C$13,MATCH(J94,validador!$B$2:$B$13,0)),"") -> Prospecção | L94: =IF(E94="","",YEAR(E94)&""&RIGHT("0"&MONTH(E94),2)) -> 202610
A95: 256.142.820-68 | B95: ANTONIO CARLOS CORTINA | C95: TPO INSS 50,00 A 150,00 | D95: 2.14 CREDIAGORA TENENTE PORTELA | E95: 46296.414 | F95: Cliente em negociaÃ§Ã£o | G95: kelen.tnp | H95: (55)99943204300false | I95: (55)999432043 | J95: =IFERROR(INDEX(validador!$B$2:$B$13,MATCH(F95,validador!$A$2:$A$13,0)),"") -> Cliente em negociação | K95: =IFERROR(INDEX(validador!$C$2:$C$13,MATCH(J95,validador!$B$2:$B$13,0)),"") -> Ligação | L95: =IF(E95="","",YEAR(E95)&""&RIGHT("0"&MONTH(E95),2)) -> 202610
A96: 044.519.560-64 | B96: MARINA VITORIA MARTENS | C96: TPO INSS 50,00 A 150,00 | D96: 2.14 CREDIAGORA TENENTE PORTELA | E96: 46296.414 | F96: Cliente com restriÃ§Ã£o | G96: anapaula | H96: (55)996698372 | I96: (55)996698372 | J96: =IFERROR(INDEX(validador!$B$2:$B$13,MATCH(F96,validador!$A$2:$A$13,0)),"") -> Cliente com restrição | K96: =IFERROR(INDEX(validador!$C$2:$C$13,MATCH(J96,validador!$B$2:$B$13,0)),"") -> Cliente com restrição | L96: =IF(E96="","",YEAR(E96)&""&RIGHT("0"&MONTH(E96),2)) -> 202610
A97: 902.548.640-15 | B97: VALDENIR FREITAS | C97: Receptivo PAR | D97: 3.01 PARATYCRED | E97: 46296.414 | F97: ProspecÃ§Ã£o | G97: bruna_jesus | H97: (55)991792602 | I97: (55)991792602 | J97: =IFERROR(INDEX(validador!$B$2:$B$13,MATCH(F97,validador!$A$2:$A$13,0)),"") -> Prospecção | K97: =IFERROR(INDEX(validador!$C$2:$C$13,MATCH(J97,validador!$B$2:$B$13,0)),"") -> Prospecção | L97: =IF(E97="","",YEAR(E97)&""&RIGHT("0"&MONTH(E97),2)) -> 202610
A98: 036.797.070-88 | B98: RODRIGO KOCHE | C98: Receptivo SCR | D98: 2.05 CREDIAGORA SANTO CRISTO | E98: 46296.414 | F98: ProspecÃ§Ã£o | G98: amanda.m | H98: (55)996886198 | I98: (55)996886198 | J98: =IFERROR(INDEX(validador!$B$2:$B$13,MATCH(F98,validador!$A$2:$A$13,0)),"") -> Prospecção | K98: =IFERROR(INDEX(validador!$C$2:$C$13,MATCH(J98,validador!$B$2:$B$13,0)),"") -> Prospecção | L98: =IF(E98="","",YEAR(E98)&""&RIGHT("0"&MONTH(E98),2)) -> 202610
A99: 932.263.570-34 | B99: LEANDRO MANHABOSCO | C99: TPO INSS 50,00 A 150,00 | D99: 2.14 CREDIAGORA TENENTE PORTELA | E99: 46296.415 | F99: Cliente sem interesse | G99: kelen.tnp | I99: (55)996733503 | J99: =IFERROR(INDEX(validador!$B$2:$B$13,MATCH(F99,validador!$A$2:$A$13,0)),"") -> Cliente sem interesse | K99: =IFERROR(INDEX(validador!$C$2:$C$13,MATCH(J99,validador!$B$2:$B$13,0)),"") -> Ligação | L99: =IF(E99="","",YEAR(E99)&""&RIGHT("0"&MONTH(E99),2)) -> 202610
A100: 287.817.750-91 | B100: LEO GUARACI DA SILVEIRA CORREA | C100: Receptivo PAR | D100: 3.01 PARATYCRED | E100: 46296.415 | F100: ProspecÃ§Ã£o | G100: bruna_jesus | H100: (55)981168281 | I100: (55)981168281 | J100: =IFERROR(INDEX(validador!$B$2:$B$13,MATCH(F100,validador!$A$2:$A$13,0)),"") -> Prospecção | K100: =IFERROR(INDEX(validador!$C$2:$C$13,MATCH(J100,validador!$B$2:$B$13,0)),"") -> Prospecção | L100: =IF(E100="","",YEAR(E100)&""&RIGHT("0"&MONTH(E100),2)) -> 202610
A101: 420.304.710-20 | B101: SIRIA MARLI MARQUESIN | C101: TPO INSS 50,00 A 150,00 | D101: 2.14 CREDIAGORA TENENTE PORTELA | E101: 46296.415 | F101: Cliente sem interesse | G101: kelen.tnp | H101: (55)35511684 | I101: (55)999212162 | J101: =IFERROR(INDEX(validador!$B$2:$B$13,MATCH(F101,validador!$A$2:$A$13,0)),"") -> Cliente sem interesse | K101: =IFERROR(INDEX(validador!$C$2:$C$13,MATCH(J101,validador!$B$2:$B$13,0)),"") -> Ligação | L101: =IF(E101="","",YEAR(E101)&""&RIGHT("0"&MONTH(E101),2)) -> 202610
A102: 047.008.780-37 | B102: BRUNA WAGNER DOS SANTOS | C102: Receptivo SCR | D102: 2.05 CREDIAGORA SANTO CRISTO | E102: 46296.415 | F102: ProspecÃ§Ã£o | G102: amanda.m | H102: (55)984760119 | I102: (55)989898697 | J102: =IFERROR(INDEX(validador!$B$2:$B$13,MATCH(F102,validador!$A$2:$A$13,0)),"") -> Prospecção | K102: =IFERROR(INDEX(validador!$C$2:$C$13,MATCH(J102,validador!$B$2:$B$13,0)),"") -> Prospecção | L102: =IF(E102="","",YEAR(E102)&""&RIGHT("0"&MONTH(E102),2)) -> 202610
A103: 549.684.880-68 | B103: CLENIR SILVA BARRETO | C103: Receptivo SBO | D103: 2.02 CREDIAGORA SAO BORJA | E103: 46296.416 | F103: Cliente em negociaÃ§Ã£o | G103: ana.rodrigues | H103: (51)998870657 | I103: (51)998870657 | J103: =IFERROR(INDEX(validador!$B$2:$B$13,MATCH(F103,validador!$A$2:$A$13,0)),"") -> Cliente em negociação | K103: =IFERROR(INDEX(validador!$C$2:$C$13,MATCH(J103,validador!$B$2:$B$13,0)),"") -> Ligação | L103: =IF(E103="","",YEAR(E103)&""&RIGHT("0"&MONTH(E103),2)) -> 202610
A104: 955.304.010-15 | B104: EVANDRO FERRI | C104: TPO INSS 50,00 A 150,00 | D104: 2.14 CREDIAGORA TENENTE PORTELA | E104: 46296.416 | F104: Cliente em negociaÃ§Ã£o | G104: anapaula | H104: (55)999619353 | I104: (55)999619353 | J104: =IFERROR(INDEX(validador!$B$2:$B$13,MATCH(F104,validador!$A$2:$A$13,0)),"") -> Cliente em negociação | K104: =IFERROR(INDEX(validador!$C$2:$C$13,MATCH(J104,validador!$B$2:$B$13,0)),"") -> Ligação | L104: =IF(E104="","",YEAR(E104)&""&RIGHT("0"&MONTH(E104),2)) -> 202610
A105: 685.603.700-72 | B105: MARIZA GARCIA MACHADO | C105: Receptiva SAN | D105: 2.13 CREDIAGORA SANTO ANGELO | E105: 46296.416 | F105: ProspecÃ§Ã£o | G105: nicoli.gb | H105: (55)3313659200false | I105: (55)999314149 | J105: =IFERROR(INDEX(validador!$B$2:$B$13,MATCH(F105,validador!$A$2:$A$13,0)),"") -> Prospecção | K105: =IFERROR(INDEX(validador!$C$2:$C$13,MATCH(J105,validador!$B$2:$B$13,0)),"") -> Prospecção | L105: =IF(E105="","",YEAR(E105)&""&RIGHT("0"&MONTH(E105),2)) -> 202610
A106: 534.559.590-91 | B106: MARGARETE CORREA DE OLIVEIRA | C106: TPO INSS 50,00 A 150,00 | D106: 2.14 CREDIAGORA TENENTE PORTELA | E106: 46296.417 | F106: Cliente em negociaÃ§Ã£o | G106: anapaula | H106: (55)999428677 | I106: (55)999428677 | J106: =IFERROR(INDEX(validador!$B$2:$B$13,MATCH(F106,validador!$A$2:$A$13,0)),"") -> Cliente em negociação | K106: =IFERROR(INDEX(validador!$C$2:$C$13,MATCH(J106,validador!$B$2:$B$13,0)),"") -> Ligação | L106: =IF(E106="","",YEAR(E106)&""&RIGHT("0"&MONTH(E106),2)) -> 202610
A107: 043.738.450-00 | B107: FERNANDO AUGUSTO BATISTA ZEPPE | C107: Receptivo SCR | D107: 2.05 CREDIAGORA SANTO CRISTO | E107: 46296.418 | F107: ProspecÃ§Ã£o | G107: patricia.eu | H107: (55)996939145 | I107: (55)996939145 | J107: =IFERROR(INDEX(validador!$B$2:$B$13,MATCH(F107,validador!$A$2:$A$13,0)),"") -> Prospecção | K107: =IFERROR(INDEX(validador!$C$2:$C$13,MATCH(J107,validador!$B$2:$B$13,0)),"") -> Prospecção | L107: =IF(E107="","",YEAR(E107)&""&RIGHT("0"&MONTH(E107),2)) -> 202610
A108: 001.314.960-18 | B108: LUCAS BROCH SOARES | C108: Receptivo ALEG | D108: 2.10 CREDIAGORA ALEGRETE | E108: 46296.418 | F108: Cliente com restriÃ§Ã£o | G108: queilla.r | H108: (55)997243830 | I108: (55)997243830 | J108: =IFERROR(INDEX(validador!$B$2:$B$13,MATCH(F108,validador!$A$2:$A$13,0)),"") -> Cliente com restrição | K108: =IFERROR(INDEX(validador!$C$2:$C$13,MATCH(J108,validador!$B$2:$B$13,0)),"") -> Cliente com restrição | L108: =IF(E108="","",YEAR(E108)&""&RIGHT("0"&MONTH(E108),2)) -> 202610
A109: 975.864.710-53 | B109: RICARDO FERNANDES DA SILVA | C109: Receptivo PAR | D109: 3.01 PARATYCRED | E109: 46296.419 | F109: ProspecÃ§Ã£o | G109: bruna_jesus | H109: (55)996057561 | I109: (55)996057561 | J109: =IFERROR(INDEX(validador!$B$2:$B$13,MATCH(F109,validador!$A$2:$A$13,0)),"") -> Prospecção | K109: =IFERROR(INDEX(validador!$C$2:$C$13,MATCH(J109,validador!$B$2:$B$13,0)),"") -> Prospecção | L109: =IF(E109="","",YEAR(E109)&""&RIGHT("0"&MONTH(E109),2)) -> 202610
A110: 003.159.000-40 | B110: MARIA SIMONE FORMENTIN OLIVEIRA | C110: Receptiva SRO | D110: 2.01 CREDIAGORA SANTA ROSA | E110: 46296.42 | F110: Cliente sem margem_INSS | G110: camila.b | I110: (53)984099209 | J110: =IFERROR(INDEX(validador!$B$2:$B$13,MATCH(F110,validador!$A$2:$A$13,0)),"") -> Cliente sem margem INSS | K110: =IFERROR(INDEX(validador!$C$2:$C$13,MATCH(J110,validador!$B$2:$B$13,0)),"") -> Cliente sem margem INSS | L110: =IF(E110="","",YEAR(E110)&""&RIGHT("0"&MONTH(E110),2)) -> 202610
A111: 010.004.090-07 | B111: IRACI FRANCISCA MONTEIRO DE SOUZA | C111: PARATY ENT JAN A JUNHO | D111: 3.01 PARATYCRED | E111: 46296.42 | F111: Telefone invÃ¡lido | G111: andre.prt | H111: (55)98135048100false | I111: (55)981350481 | J111: =IFERROR(INDEX(validador!$B$2:$B$13,MATCH(F111,validador!$A$2:$A$13,0)),"") -> Telefone inválido | K111: =IFERROR(INDEX(validador!$C$2:$C$13,MATCH(J111,validador!$B$2:$B$13,0)),"") -> Telefone inválido | L111: =IF(E111="","",YEAR(E111)&""&RIGHT("0"&MONTH(E111),2)) -> 202610
A112: 019.842.850-25 | B112: JOAO FERNANDO SEIMETZ | C112: SRO crédito pessoal | D112: 2.01 CREDIAGORA SANTA ROSA | E112: 46296.42 | F112: Retornar ligaÃ§Ã£o | G112: fabiane | H112: (55)999378856 | I112: (55)999113681 | J112: =IFERROR(INDEX(validador!$B$2:$B$13,MATCH(F112,validador!$A$2:$A$13,0)),"") -> Retornar ligação | K112: =IFERROR(INDEX(validador!$C$2:$C$13,MATCH(J112,validador!$B$2:$B$13,0)),"") -> Retornar ligação | L112: =IF(E112="","",YEAR(E112)&""&RIGHT("0"&MONTH(E112),2)) -> 202610
A113: 825.149.840-68 | B113: TERESINHA MARGARETE RAMOS LAZAROTTO | C113: Credito Pessoal URU | D113: 3.02 CREDIAGORA URUGUAIANA | E113: 46296.42 | F113: ProspecÃ§Ã£o | G113: andreia.rospa | I113: (55)992016327 | J113: =IFERROR(INDEX(validador!$B$2:$B$13,MATCH(F113,validador!$A$2:$A$13,0)),"") -> Prospecção | K113: =IFERROR(INDEX(validador!$C$2:$C$13,MATCH(J113,validador!$B$2:$B$13,0)),"") -> Prospecção | L113: =IF(E113="","",YEAR(E113)&""&RIGHT("0"&MONTH(E113),2)) -> 202610
A114: 569.311.660-34 | B114: ASSIS FERNANDO MARTINS LENCINA | C114: Receptivo SBO | D114: 2.02 CREDIAGORA SAO BORJA | E114: 46296.42 | F114: ProspecÃ§Ã£o | G114: ana.rodrigues | H114: (55)99638417500false | I114: (55)996384175 | J114: =IFERROR(INDEX(validador!$B$2:$B$13,MATCH(F114,validador!$A$2:$A$13,0)),"") -> Prospecção | K114: =IFERROR(INDEX(validador!$C$2:$C$13,MATCH(J114,validador!$B$2:$B$13,0)),"") -> Prospecção | L114: =IF(E114="","",YEAR(E114)&""&RIGHT("0"&MONTH(E114),2)) -> 202610
A115: 044.785.890-46 | B115: MINEIA VANESSA ROBE | C115: Receptivo SCR | D115: 2.05 CREDIAGORA SANTO CRISTO | E115: 46296.421 | F115: contrato ativo/ limite disponivel | G115: amanda.m | H115: (55)997037176 | I115: (55)997037176 | J115: =IFERROR(INDEX(validador!$B$2:$B$13,MATCH(F115,validador!$A$2:$A$13,0)),"") -> Contrato ativo/limite disponivel | K115: =IFERROR(INDEX(validador!$C$2:$C$13,MATCH(J115,validador!$B$2:$B$13,0)),"") -> Contrato ativo/limite disponivel | L115: =IF(E115="","",YEAR(E115)&""&RIGHT("0"&MONTH(E115),2)) -> 202610
A116: 823.561.220-87 | B116: SUELI LEBTAG | C116: SAN INSS 30+ | D116: 2.13 CREDIAGORA SANTO ANGELO | E116: 46296.421 | F116: ProspecÃ§Ã£o | G116: lucimara.stiler | H116: (55)99914891500false | I116: (55)999148915 | J116: =IFERROR(INDEX(validador!$B$2:$B$13,MATCH(F116,validador!$A$2:$A$13,0)),"") -> Prospecção | K116: =IFERROR(INDEX(validador!$C$2:$C$13,MATCH(J116,validador!$B$2:$B$13,0)),"") -> Prospecção | L116: =IF(E116="","",YEAR(E116)&""&RIGHT("0"&MONTH(E116),2)) -> 202610
A117: 044.785.890-46 | B117: MINEIA VANESSA ROBE | C117: Receptivo SCR | D117: 2.05 CREDIAGORA SANTO CRISTO | E117: 46296.421 | F117: ProspecÃ§Ã£o | G117: amanda.m | H117: (55)997037176 | I117: (55)997037176 | J117: =IFERROR(INDEX(validador!$B$2:$B$13,MATCH(F117,validador!$A$2:$A$13,0)),"") -> Prospecção | K117: =IFERROR(INDEX(validador!$C$2:$C$13,MATCH(J117,validador!$B$2:$B$13,0)),"") -> Prospecção | L117: =IF(E117="","",YEAR(E117)&""&RIGHT("0"&MONTH(E117),2)) -> 202610
A118: 673.496.419-15 | B118: LONI DOLORES DOEBBER | C118: Receptivo SCR | D118: 2.05 CREDIAGORA SANTO CRISTO | E118: 46296.421 | F118: ProspecÃ§Ã£o | G118: patricia.eu | H118: (55)981315518020false | I118: (55)981315518 | J118: =IFERROR(INDEX(validador!$B$2:$B$13,MATCH(F118,validador!$A$2:$A$13,0)),"") -> Prospecção | K118: =IFERROR(INDEX(validador!$C$2:$C$13,MATCH(J118,validador!$B$2:$B$13,0)),"") -> Prospecção | L118: =IF(E118="","",YEAR(E118)&""&RIGHT("0"&MONTH(E118),2)) -> 202610
A119: 519.481.681-20 | B119: RONALDO SCREMIN PAIM | C119: SAN INSS 30+ | D119: 2.13 CREDIAGORA SANTO ANGELO | E119: 46296.422 | F119: Cliente sem interesse | G119: lucimara.stiler | H119: (67)99865153400false | I119: (55)981219852 | J119: =IFERROR(INDEX(validador!$B$2:$B$13,MATCH(F119,validador!$A$2:$A$13,0)),"") -> Cliente sem interesse | K119: =IFERROR(INDEX(validador!$C$2:$C$13,MATCH(J119,validador!$B$2:$B$13,0)),"") -> Ligação | L119: =IF(E119="","",YEAR(E119)&""&RIGHT("0"&MONTH(E119),2)) -> 202610
A120: 305.491.240-04 | B120: MARLI FATIMA CHIESA BENDER | C120: CRUZ ALTA INSS 50 A 200 | D120: 3.03 CREDIAGORA CRUZ ALTA | E120: 46296.422 | F120: Cliente sem interesse | G120: gabriele.sg | H120: (55)99945410170false | I120: (55)996031612 | J120: =IFERROR(INDEX(validador!$B$2:$B$13,MATCH(F120,validador!$A$2:$A$13,0)),"") -> Cliente sem interesse | K120: =IFERROR(INDEX(validador!$C$2:$C$13,MATCH(J120,validador!$B$2:$B$13,0)),"") -> Ligação | L120: =IF(E120="","",YEAR(E120)&""&RIGHT("0"&MONTH(E120),2)) -> 202610
A121: 983.965.440-34 | B121: RESOLI DE MORAES DA SILVA | C121: Credito Pessoal URU | D121: 3.02 CREDIAGORA URUGUAIANA | E121: 46296.422 | F121: ProspecÃ§Ã£o | G121: andreia.rospa | H121: (55)32422921 | I121: (55)999880932 | J121: =IFERROR(INDEX(validador!$B$2:$B$13,MATCH(F121,validador!$A$2:$A$13,0)),"") -> Prospecção | K121: =IFERROR(INDEX(validador!$C$2:$C$13,MATCH(J121,validador!$B$2:$B$13,0)),"") -> Prospecção | L121: =IF(E121="","",YEAR(E121)&""&RIGHT("0"&MONTH(E121),2)) -> 202610
A122: 418.011.300-78 | B122: ADAO VANDERLEI DE ALMEIDA | C122: Receptivo SFA | D122: 2.18 CREDIAGORA SAO FRANCISCO DE ASSIS | E122: 46296.423 | F122: Aceitou NegociaÃ§Ã£o | G122: nivia.oleiniczak | H122: (55)996561098 | I122: (55)996561098 | J122: =IFERROR(INDEX(validador!$B$2:$B$13,MATCH(F122,validador!$A$2:$A$13,0)),"") -> Aceitou Negociação | K122: =IFERROR(INDEX(validador!$C$2:$C$13,MATCH(J122,validador!$B$2:$B$13,0)),"") -> Ligação | L122: =IF(E122="","",YEAR(E122)&""&RIGHT("0"&MONTH(E122),2)) -> 202610
A123: 505.940.600-87 | B123: WALMOR ANTONIO GABBI | C123: Credito Pessoal URU | D123: 3.02 CREDIAGORA URUGUAIANA | E123: 46296.423 | F123: ProspecÃ§Ã£o | G123: andreia.rospa | H123: (55)999068418 | I123: (55)999068418 | J123: =IFERROR(INDEX(validador!$B$2:$B$13,MATCH(F123,validador!$A$2:$A$13,0)),"") -> Prospecção | K123: =IFERROR(INDEX(validador!$C$2:$C$13,MATCH(J123,validador!$B$2:$B$13,0)),"") -> Prospecção | L123: =IF(E123="","",YEAR(E123)&""&RIGHT("0"&MONTH(E123),2)) -> 202610
A124: 908.482.410-53 | B124: CENI DOS SANTOS FERREIRA | C124: TPO INSS 50,00 A 150,00 | D124: 2.14 CREDIAGORA TENENTE PORTELA | E124: 46296.423 | F124: Cliente em negociaÃ§Ã£o | G124: kelen.tnp | H124: (15)33225050 | I124: (55)996535977 | J124: =IFERROR(INDEX(validador!$B$2:$B$13,MATCH(F124,validador!$A$2:$A$13,0)),"") -> Cliente em negociação | K124: =IFERROR(INDEX(validador!$C$2:$C$13,MATCH(J124,validador!$B$2:$B$13,0)),"") -> Ligação | L124: =IF(E124="","",YEAR(E124)&""&RIGHT("0"&MONTH(E124),2)) -> 202610
A125: 711.812.290-49 | B125: CLAUDIA SALETE BRITES | C125: TPO INSS 50,00 A 150,00 | D125: 2.14 CREDIAGORA TENENTE PORTELA | E125: 46296.424 | F125: envio de whatsapp | G125: anapaula | H125: (55)999674402 | I125: (55)999674402 | J125: =IFERROR(INDEX(validador!$B$2:$B$13,MATCH(F125,validador!$A$2:$A$13,0)),"") -> Envio de Whatsapp | K125: =IFERROR(INDEX(validador!$C$2:$C$13,MATCH(J125,validador!$B$2:$B$13,0)),"") -> Envio de Whatsapp | L125: =IF(E125="","",YEAR(E125)&""&RIGHT("0"&MONTH(E125),2)) -> 202610
... A133: 032.219.690-66 | B133: DAVI DA SILVA ALVES | C133: Receptiva URU | D133: 3.02 CREDIAGORA URUGUAIANA | E133: 46296.427 | F133: ProspecÃ§Ã£o | G133: fernanda.lannes | H133: (55)999202821 | I133: (55)999202821 | J133: =IFERROR(INDEX(validador!$B$2:$B$13,MATCH(F133,validador!$A$2:$A$13,0)),"") -> Prospecção | K133: =IFERROR(INDEX(validador!$C$2:$C$13,MATCH(J133,validador!$B$2:$B$13,0)),"") -> Prospecção | L133: =IF(E133="","",YEAR(E133)&""&RIGHT("0"&MONTH(E133),2)) -> 202610
A134: 105.669.105-01 | B134: ELIOMAR DA SILVEIRA | C134: TPO INSS 50,00 A 150,00 | D134: 2.14 CREDIAGORA TENENTE PORTELA | E134: 46296.427 | F134: Cliente sem interesse | G134: anapaula | J134: =IFERROR(INDEX(validador!$B$2:$B$13,MATCH(F134,validador!$A$2:$A$13,0)),"") -> Cliente sem interesse | K134: =IFERROR(INDEX(validador!$C$2:$C$13,MATCH(J134,validador!$B$2:$B$13,0)),"") -> Ligação | L134: =IF(E134="","",YEAR(E134)&""&RIGHT("0"&MONTH(E134),2)) -> 202610
A135: 013.747.920-47 | B135: CLEBSON ANDRE DOS SANTOS RODRIGUES | C135: SRO crédito pessoal | D135: 2.01 CREDIAGORA SANTA ROSA | E135: 46296.428 | F135: Retornar ligaÃ§Ã£o | G135: fabiane | H135: (55)21428613 | I135: (55)999820283 | J135: =IFERROR(INDEX(validador!$B$2:$B$13,MATCH(F135,validador!$A$2:$A$13,0)),"") -> Retornar ligação | K135: =IFERROR(INDEX(validador!$C$2:$C$13,MATCH(J135,validador!$B$2:$B$13,0)),"") -> Retornar ligação | L135: =IF(E135="","",YEAR(E135)&""&RIGHT("0"&MONTH(E135),2)) -> 202610
A136: 003.466.020-84 | B136: LUIS CLAUDIO DA SILVA CORREA | C136: SRO crédito pessoal | D136: 2.01 CREDIAGORA SANTA ROSA | E136: 46296.428 | F136: Retornar ligaÃ§Ã£o | G136: fabiane | H136: (55)984038365 | I136: (55)984038365 | J136: =IFERROR(INDEX(validador!$B$2:$B$13,MATCH(F136,validador!$A$2:$A$13,0)),"") -> Retornar ligação | K136: =IFERROR(INDEX(validador!$C$2:$C$13,MATCH(J136,validador!$B$2:$B$13,0)),"") -> Retornar ligação | L136: =IF(E136="","",YEAR(E136)&""&RIGHT("0"&MONTH(E136),2)) -> 202610
A137: 680.933.810-15 | B137: CLAIRTO MARTIN | C137: Receptiva SRO | D137: 2.01 CREDIAGORA SANTA ROSA | E137: 46296.428 | F137: Cliente em negociaÃ§Ã£o | G137: TALIAF | H137: (55)981383980 | I137: (55)981383980 | J137: =IFERROR(INDEX(validador!$B$2:$B$13,MATCH(F137,validador!$A$2:$A$13,0)),"") -> Cliente em negociação | K137: =IFERROR(INDEX(validador!$C$2:$C$13,MATCH(J137,validador!$B$2:$B$13,0)),"") -> Ligação | L137: =IF(E137="","",YEAR(E137)&""&RIGHT("0"&MONTH(E137),2)) -> 202610
A138: 384.911.760-04 | B138: JOSE ELEMAR KOTZ | C138: SRO crédito pessoal | D138: 2.01 CREDIAGORA SANTA ROSA | E138: 46296.428 | F138: Retornar ligaÃ§Ã£o | G138: fabiane | H138: (55)996997292 | I138: (55)996997292 | J138: =IFERROR(INDEX(validador!$B$2:$B$13,MATCH(F138,validador!$A$2:$A$13,0)),"") -> Retornar ligação | K138: =IFERROR(INDEX(validador!$C$2:$C$13,MATCH(J138,validador!$B$2:$B$13,0)),"") -> Retornar ligação | L138: =IF(E138="","",YEAR(E138)&""&RIGHT("0"&MONTH(E138),2)) -> 202610
A139: 040.631.150-11 | B139: ROBSON DIEGO PISZXZALKA | C139: SRO crédito pessoal | D139: 2.01 CREDIAGORA SANTA ROSA | E139: 46296.429 | F139: Retornar ligaÃ§Ã£o | G139: fabiane | H139: (55)991896961 | I139: (55)991896961 | J139: =IFERROR(INDEX(validador!$B$2:$B$13,MATCH(F139,validador!$A$2:$A$13,0)),"") -> Retornar ligação | K139: =IFERROR(INDEX(validador!$C$2:$C$13,MATCH(J139,validador!$B$2:$B$13,0)),"") -> Retornar ligação | L139: =IF(E139="","",YEAR(E139)&""&RIGHT("0"&MONTH(E139),2)) -> 202610
A140: 900.208.630-04 | B140: MARCOS ROBERTO SEVERO PEREIRA | C140: ALE CLT | D140: 2.10 CREDIAGORA ALEGRETE | E140: 46296.429 | F140: envio de whatsapp | G140: queilla.r | H140: (55)99666262800false | I140: (55)996662628 | J140: =IFERROR(INDEX(validador!$B$2:$B$13,MATCH(F140,validador!$A$2:$A$13,0)),"") -> Envio de Whatsapp | K140: =IFERROR(INDEX(validador!$C$2:$C$13,MATCH(J140,validador!$B$2:$B$13,0)),"") -> Envio de Whatsapp | L140: =IF(E140="","",YEAR(E140)&""&RIGHT("0"&MONTH(E140),2)) -> 202610
A141: 290.364.290-72 | B141: ELDEGARD HOFFERBER | C141: Receptiva SRO | D141: 2.01 CREDIAGORA SANTA ROSA | E141: 46296.429 | F141: ProspecÃ§Ã£o | G141: TALIAF | H141: (55)35111688 | I141: (55)997065551 | J141: =IFERROR(INDEX(validador!$B$2:$B$13,MATCH(F141,validador!$A$2:$A$13,0)),"") -> Prospecção | K141: =IFERROR(INDEX(validador!$C$2:$C$13,MATCH(J141,validador!$B$2:$B$13,0)),"") -> Prospecção | L141: =IF(E141="","",YEAR(E141)&""&RIGHT("0"&MONTH(E141),2)) -> 202610
...

Sheet validador
A1: Status | B1: STATUS CORRETO | C1: CONSIDERAR
A2: ProspecÃ§Ã£o | B2: Prospecção | C2: Prospecção
A3: Cliente sem interesse | B3: Cliente sem interesse | C3: Ligação
A4: Cliente sem margem_INSS | B4: Cliente sem margem INSS | C4: Cliente sem margem INSS
A5: contrato ativo/ limite disponivel | B5: Contrato ativo/limite disponivel | C5: Contrato ativo/limite disponivel
A6: envio de whatsapp | B6: Envio de Whatsapp | C6: Envio de Whatsapp
A7: Aceitou NegociaÃ§Ã£o | B7: Aceitou Negociação | C7: Ligação
A8: Telefone invÃ¡lido | B8: Telefone inválido | C8: Telefone inválido
A9: Cliente com restriÃ§Ã£o | B9: Cliente com restrição | C9: Cliente com restrição
A10: Retornar ligaÃ§Ã£o | B10: Retornar ligação | C10: Retornar ligação
A11: Cliente em negociaÃ§Ã£o | B11: Cliente em negociação | C11: Ligação
A12: Agendado atendimento em loja | B12: Agendado atendimento em loja | C12: Ligação
A13: FALECIDO | B13: Falecido | C13: Falecido

Sheet onde_exportar
B2: Panorama >>
B3: Click na logo Crediagora >>
B13: Substituir apenas mês atual >>
